Workbook

Sheet Inputs
A1: Boss Key Financial Architecture Model
A2: Scenario Selection | B2: Moderate | D2: Use dropdown in B2
A4: Assumption | B4: Conservative | C4: Moderate | D4: Selected
A5: Business Retainer Clients (avg) | B5: 4 | C5: 4 | D5: =IF($B$2="Conservative",B5,C5) -> 4
A6: Seller Retainer Clients (avg) | B6: 0.5 | C6: 1 | D6: =IF($B$2="Conservative",B6,C6) -> 1
A7: Avg Business Retainer ($/mo) | B7: 5600 | C7: 5750 | D7: =IF($B$2="Conservative",B7,C7) -> 5750
A8: Avg Seller Retainer ($/mo) | B8: 2400 | C8: 2500 | D8: =IF($B$2="Conservative",B8,C8) -> 2500
A9: Business Diagnostics per Year | B9: 6 | C9: 6 | D9: =IF($B$2="Conservative",B9,C9) -> 6
A10: Avg Business Diagnostic Fee ($) | B10: 5200 | C10: 5500 | D10: =IF($B$2="Conservative",B10,C10) -> 5500
A11: Seller Diagnostics per Year | B11: 3 | C11: 4 | D11: =IF($B$2="Conservative",B11,C11) -> 4
A12: Avg Seller Diagnostic Fee ($) | B12: 1600 | C12: 1750 | D12: =IF($B$2="Conservative",B12,C12) -> 1750
A13: Non-Owner Overhead ($/yr) | B13: 45000 | C13: 45000 | D13: =IF($B$2="Conservative",B13,C13) -> 45000
A14: Reasonable Salary ($/yr) | B14: 130000 | C14: 140000 | D14: =IF($B$2="Conservative",B14,C14) -> 140000
A15: Employer Payroll Tax Rate | B15: 0.0765 | C15: 0.0765 | D15: =IF($B$2="Conservative",B15,C15) -> 0.0765
A16: Federal Effective Tax Rate | B16: 0.21 | C16: 0.23 | D16: =IF($B$2="Conservative",B16,C16) -> 0.23
... A19: Operating Buffer Target % of Revenue | B19: 0.15 | C19: 0.15 | D19: =IF($B$2="Conservative",B19,C19) -> 0.15
A22: Target Annual Revenue | B22: 350000
A23: Prior W-2 Salary Reference | B23: 164000

Sheet Annual_Model
A1: Annual Financial Architecture
A3: Metric | B3: Formula/Driver | C3: Amount | D3: Notes
A4: Retainer Revenue | B4: =(Inputs!D5*Inputs!D7 + Inputs!D6*Inputs!D8)*12 -> 306000 | C4: =(Inputs!D5*Inputs!D7 + Inputs!D6*Inputs!D8)*12 -> 306000 | D4: Business + seller retainers
A5: Diagnostic Revenue | B5: =Inputs!D9*Inputs!D10 + Inputs!D11*Inputs!D12 -> 40000 | C5: =Inputs!D9*Inputs!D10 + Inputs!D11*Inputs!D12 -> 40000 | D5: Business + seller diagnostics
A6: Gross Revenue | B6: =C4+C5 -> 346000 | C6: =C4+C5 -> 346000
A7: Non-Owner Overhead | B7: =Inputs!D13 -> 45000 | C7: =Inputs!D13 -> 45000
A8: Pre-Owner Comp Operating Profit | B8: =C6-C7 -> 301000 | C8: =C6-C7 -> 301000
A9: Reasonable Salary | B9: =Inputs!D14 -> 140000 | C9: =Inputs!D14 -> 140000
A10: Employer Payroll Tax | B10: =C9*Inputs!D15 -> 10710 | C10: =C9*Inputs!D15 -> 10710
A11: S-Corp Profit (Pre-Income Tax) | B11: =C8-C9-C10 -> 150290 | C11: =C8-C9-C10 -> 150290
A12: Combined Effective Tax Rate | B12: =Inputs!D16+Inputs!D17 -> 0.295 | C12: =Inputs!D16+Inputs!D17 -> 0.295
A13: Estimated Income Tax on Salary + Profit | B13: =(C9+C11)*C12 -> 85635.55 | C13: =(C9+C11)*C12 -> 85635.55 | D13: Planning estimate
A14: Estimated After-Tax Owner Cash | B14: =C9+C11-C13 -> 204654.45 | C14: =C9+C11-C13 -> 204654.45 | D14: Salary + distributions net of est tax
A15: Operating Buffer Target | B15: =C6*Inputs!D19 -> 51900 | C15: =C6*Inputs!D19 -> 51900

Sheet Monthly_Cashflow
A1: Monthly Cash Flow Discipline (Planning)
A3: Month | B3: Revenue | C3: Overhead | D3: Salary | E3: Employer Payroll Tax | F3: Pre-Tax Profit | G3: Tax Reserve Transfer | H3: Owner Distribution (Gross) | I3: Ending Operating Buffer | J3: Notes
A4: Jan | B4: =Annual_Model!C6/12 -> 28833.333 | C4: =Inputs!D13/12 -> 3750 | D4: =Inputs!D14/12 -> 11666.667 | E4: =D4*Inputs!D15 -> 892.5 | F4: =B4-C4-D4-E4 -> 12524.167 | G4: =MAX(0,F4*Inputs!D18) -> 4759.1833 | H4: =MAX(0,F4-G4) -> 7764.9833 | I4: =Inputs!B22*Inputs!D19/2 + H4 -> 34014.983
A5: Feb | B5: =Annual_Model!C6/12 -> 28833.333 | C5: =Inputs!D13/12 -> 3750 | D5: =Inputs!D14/12 -> 11666.667 | E5: =D5*Inputs!D15 -> 892.5 | F5: =B5-C5-D5-E5 -> 12524.167 | G5: =MAX(0,F5*Inputs!D18) -> 4759.1833 | H5: =MAX(0,F5-G5) -> 7764.9833 | I5: =I4+H5 -> 41779.967
A6: Mar | B6: =Annual_Model!C6/12 -> 28833.333 | C6: =Inputs!D13/12 -> 3750 | D6: =Inputs!D14/12 -> 11666.667 | E6: =D6*Inputs!D15 -> 892.5 | F6: =B6-C6-D6-E6 -> 12524.167 | G6: =MAX(0,F6*Inputs!D18) -> 4759.1833 | H6: =MAX(0,F6-G6) -> 7764.9833 | I6: =I5+H6 -> 49544.95
A7: Apr | B7: =Annual_Model!C6/12 -> 28833.333 | C7: =Inputs!D13/12 -> 3750 | D7: =Inputs!D14/12 -> 11666.667 | E7: =D7*Inputs!D15 -> 892.5 | F7: =B7-C7-D7-E7 -> 12524.167 | G7: =MAX(0,F7*Inputs!D18) -> 4759.1833 | H7: =MAX(0,F7-G7) -> 7764.9833 | I7: =I6+H7 -> 57309.933
A8: May | B8: =Annual_Model!C6/12 -> 28833.333 | C8: =Inputs!D13/12 -> 3750 | D8: =Inputs!D14/12 -> 11666.667 | E8: =D8*Inputs!D15 -> 892.5 | F8: =B8-C8-D8-E8 -> 12524.167 | G8: =MAX(0,F8*Inputs!D18) -> 4759.1833 | H8: =MAX(0,F8-G8) -> 7764.9833 | I8: =I7+H8 -> 65074.917
A9: Jun | B9: =Annual_Model!C6/12 -> 28833.333 | C9: =Inputs!D13/12 -> 3750 | D9: =Inputs!D14/12 -> 11666.667 | E9: =D9*Inputs!D15 -> 892.5 | F9: =B9-C9-D9-E9 -> 12524.167 | G9: =MAX(0,F9*Inputs!D18) -> 4759.1833 | H9: =MAX(0,F9-G9) -> 7764.9833 | I9: =I8+H9 -> 72839.9
A10: Jul | B10: =Annual_Model!C6/12 -> 28833.333 | C10: =Inputs!D13/12 -> 3750 | D10: =Inputs!D14/12 -> 11666.667 | E10: =D10*Inputs!D15 -> 892.5 | F10: =B10-C10-D10-E10 -> 12524.167 | G10: =MAX(0,F10*Inputs!D18) -> 4759.1833 | H10: =MAX(0,F10-G10) -> 7764.9833 | I10: =I9+H10 -> 80604.883
A11: Aug | B11: =Annual_Model!C6/12 -> 28833.333 | C11: =Inputs!D13/12 -> 3750 | D11: =Inputs!D14/12 -> 11666.667 | E11: =D11*Inputs!D15 -> 892.5 | F11: =B11-C11-D11-E11 -> 12524.167 | G11: =MAX(0,F11*Inputs!D18) -> 4759.1833 | H11: =MAX(0,F11-G11) -> 7764.9833 | I11: =I10+H11 -> 88369.867
A12: Sep | B12: =Annual_Model!C6/12 -> 28833.333 | C12: =Inputs!D13/12 -> 3750 | D12: =Inputs!D14/12 -> 11666.667 | E12: =D12*Inputs!D15 -> 892.5 | F12: =B12-C12-D12-E12 -> 12524.167 | G12: =MAX(0,F12*Inputs!D18) -> 4759.1833 | H12: =MAX(0,F12-G12) -> 7764.9833 | I12: =I11+H12 -> 96134.85
A13: Oct | B13: =Annual_Model!C6/12 -> 28833.333 | C13: =Inputs!D13/12 -> 3750 | D13: =Inputs!D14/12 -> 11666.667 | E13: =D13*Inputs!D15 -> 892.5 | F13: =B13-C13-D13-E13 -> 12524.167 | G13: =MAX(0,F13*Inputs!D18) -> 4759.1833 | H13: =MAX(0,F13-G13) -> 7764.9833 | I13: =I12+H13 -> 103899.83
A14: Nov | B14: =Annual_Model!C6/12 -> 28833.333 | C14: =Inputs!D13/12 -> 3750 | D14: =Inputs!D14/12 -> 11666.667 | E14: =D14*Inputs!D15 -> 892.5 | F14: =B14-C14-D14-E14 -> 12524.167 | G14: =MAX(0,F14*Inputs!D18) -> 4759.1833 | H14: =MAX(0,F14-G14) -> 7764.9833 | I14: =I13+H14 -> 111664.82
A15: Dec | B15: =Annual_Model!C6/12 -> 28833.333 | C15: =Inputs!D13/12 -> 3750 | D15: =Inputs!D14/12 -> 11666.667 | E15: =D15*Inputs!D15 -> 892.5 | F15: =B15-C15-D15-E15 -> 12524.167 | G15: =MAX(0,F15*Inputs!D18) -> 4759.1833 | H15: =MAX(0,F15-G15) -> 7764.9833 | I15: =I14+H15 -> 119429.8
A17: Annual Totals | B17: =SUM(B4:B15) -> 346000 | C17: =SUM(C4:C15) -> 45000 | D17: =SUM(D4:D15) -> 140000 | E17: =SUM(E4:E15) -> 10710 | F17: =SUM(F4:F15) -> 150290 | G17: =SUM(G4:G15) -> 57110.2 | H17: =SUM(H4:H15) -> 93179.8 | I17: =I15 -> 119429.8

Sheet Scenario_Compare
A1: Scenario Comparison (Conservative / Moderate / Strong)
A3: Metric | B3: Conservative | C3: Moderate | D3: Strong | E3: Notes
A4: Business Clients | B4: =Inputs!B5 -> 4 | C4: =Inputs!C5 -> 4 | D4: 5
A5: Seller Clients | B5: =Inputs!B6 -> 0.5 | C5: =Inputs!C6 -> 1 | D5: 1
A6: Avg Business Retainer ($/mo) | B6: =Inputs!B7 -> 5600 | C6: =Inputs!C7 -> 5750 | D6: 6000
A7: Avg Seller Retainer ($/mo) | B7: =Inputs!B8 -> 2400 | C7: =Inputs!C8 -> 2500 | D7: 2800
A8: Retainer Revenue | B8: =(B4*B6 + B5*B7)*12 -> 283200 | C8: =(C4*C6 + C5*C7)*12 -> 306000 | D8: =(D4*D6 + D5*D7)*12 -> 393600
A9: Business Diagnostics (#) | B9: =Inputs!B9 -> 6 | C9: =Inputs!C9 -> 6 | D9: 7
A10: Avg Business Diagnostic Fee | B10: =Inputs!B10 -> 5200 | C10: =Inputs!C10 -> 5500 | D10: 6000
A11: Seller Diagnostics (#) | B11: =Inputs!B11 -> 3 | C11: =Inputs!C11 -> 4 | D11: 4
A12: Avg Seller Diagnostic Fee | B12: =Inputs!B12 -> 1600 | C12: =Inputs!C12 -> 1750 | D12: 2000
A13: Diagnostic Revenue | B13: =B9*B10 + B11*B12 -> 36000 | C13: =C9*C10 + C11*C12 -> 40000 | D13: =D9*D10 + D11*D12 -> 50000
A14: Total Revenue | B14: =B8+B13 -> 319200 | C14: =C8+C13 -> 346000 | D14: =D8+D13 -> 443600

Sheet Notes
A1: Model Notes
A3: 1) This is a planning model, not tax/legal advice.
A4: 2) Change Inputs!B2 between Conservative and Moderate to toggle the model.
A5: 3) Salary level should be reviewed with CPA for reasonable compensation support.
A6: 4) Tax reserve strategy assumes disciplined quarterly set-asides.
A7: 5) Keep client roster capped to preserve delivery quality and margin.
A8: 6) Roster mix assumptions separate business and seller client economics.
A9: 7) Moderate mix target: 4 business retainers + 1 seller retainer, with 6 business and 4 seller diagnostics/year.
